{
  "project_info": {
    "project_number": "40080295503",
    "firebase_url": "https://sunriseres-5e2da.firebaseio.com",
    "project_id": "sunriseres-5e2da",
    "storage_bucket": "sunriseres-5e2da.appspot.com"
  },
  "client": [
    {
      "client_info": {
        "mobilesdk_app_id": "1:40080295503:android:696a70e2f722731d",
        "android_client_info": {
          "package_name": "com.example.sunriseres"
        }
      },
      "oauth_client": [
        {
          "client_id": "40080295503-ousl630i0g5v1j788bjuv5rgc0jcfjvr.apps.googleusercontent.com",
          "client_type": 1,
          "android_info": {
            "package_name": "com.example.sunriseres",
            "certificate_hash": "77d1565e214de64e42de1ffd90353a5e61f190f1"
          }
        },
        {
          "client_id": "40080295503-9urie9i40uuvce76e46lfvoivuog3i6f.apps.googleusercontent.com",
          "client_type": 3
        }
      ],
      "api_key": [
        {
          "current_key": "AIzaSyBNufZx3wefrAdCYzxHVqB2XISMr4P84LQ"
        }
      ],
      "services": {
        "appinvite_service": {
          "other_platform_oauth_client": [
            {
              "client_id": "40080295503-9urie9i40uuvce76e46lfvoivuog3i6f.apps.googleusercontent.com",
              "client_type": 3
            }
          ]
        }
      }
    },
    {
      "client_info": {
        "mobilesdk_app_id": "1:40080295503:android:fdb707582abcb94b",
        "android_client_info": {
          "package_name": "com.kimbrian.sunrise"
        }
      },
      "oauth_client": [
        {
          "client_id": "40080295503-d9hsrmb7hrbtnmdlldqnr8tbb35utnku.apps.googleusercontent.com",
          "client_type": 1,
          "android_info": {
            "package_name": "com.kimbrian.sunrise",
            "certificate_hash": "77d1565e214de64e42de1ffd90353a5e61f190f1"
          }
        },
        {
          "client_id": "40080295503-9urie9i40uuvce76e46lfvoivuog3i6f.apps.googleusercontent.com",
          "client_type": 3
        }
      ],
      "api_key": [
        {
          "current_key": "AIzaSyBNufZx3wefrAdCYzxHVqB2XISMr4P84LQ"
        }
      ],
      "services": {
        "appinvite_service": {
          "other_platform_oauth_client": [
            {
              "client_id": "40080295503-9urie9i40uuvce76e46lfvoivuog3i6f.apps.googleusercontent.com",
              "client_type": 3
            }
          ]
        }
      }
    }
  ],
  "configuration_version": "1"
}